main.py
azury-0.0.0.dist-info/METADATA
azury-0.0.0.dist-info/WHEEL
azury-0.0.0.dist-info/top_level.txt
azury-0.0.0.dist-info/RECORD
